odoo/addons/stock_reserve/README.rst
odoo/addons/stock_reserve/__init__.py
odoo/addons/stock_reserve/__manifest__.py
odoo/addons/stock_reserve/data/cron.xml
odoo/addons/stock_reserve/data/stock_data.xml
odoo/addons/stock_reserve/i18n/am.po
odoo/addons/stock_reserve/i18n/ar.po
odoo/addons/stock_reserve/i18n/bg.po
odoo/addons/stock_reserve/i18n/bs.po
odoo/addons/stock_reserve/i18n/ca.po
odoo/addons/stock_reserve/i18n/cs.po
odoo/addons/stock_reserve/i18n/cs_CZ.po
odoo/addons/stock_reserve/i18n/da.po
odoo/addons/stock_reserve/i18n/de.po
odoo/addons/stock_reserve/i18n/el_GR.po
odoo/addons/stock_reserve/i18n/en_GB.po
odoo/addons/stock_reserve/i18n/es.po
odoo/addons/stock_reserve/i18n/et.po
odoo/addons/stock_reserve/i18n/eu.po
odoo/addons/stock_reserve/i18n/fa.po
odoo/addons/stock_reserve/i18n/fi.po
odoo/addons/stock_reserve/i18n/fr.po
odoo/addons/stock_reserve/i18n/fr_CA.po
odoo/addons/stock_reserve/i18n/fr_CH.po
odoo/addons/stock_reserve/i18n/fr_FR.po
odoo/addons/stock_reserve/i18n/gl.po
odoo/addons/stock_reserve/i18n/gl_ES.po
odoo/addons/stock_reserve/i18n/he.po
odoo/addons/stock_reserve/i18n/hr.po
odoo/addons/stock_reserve/i18n/hr_HR.po
odoo/addons/stock_reserve/i18n/hu.po
odoo/addons/stock_reserve/i18n/id.po
odoo/addons/stock_reserve/i18n/it.po
odoo/addons/stock_reserve/i18n/ja.po
odoo/addons/stock_reserve/i18n/ko.po
odoo/addons/stock_reserve/i18n/lt.po
odoo/addons/stock_reserve/i18n/lt_LT.po
odoo/addons/stock_reserve/i18n/lv.po
odoo/addons/stock_reserve/i18n/mk.po
odoo/addons/stock_reserve/i18n/mn.po
odoo/addons/stock_reserve/i18n/nb.po
odoo/addons/stock_reserve/i18n/nb_NO.po
odoo/addons/stock_reserve/i18n/nl.po
odoo/addons/stock_reserve/i18n/nl_BE.po
odoo/addons/stock_reserve/i18n/nl_NL.po
odoo/addons/stock_reserve/i18n/pl.po
odoo/addons/stock_reserve/i18n/pt.po
odoo/addons/stock_reserve/i18n/pt_BR.po
odoo/addons/stock_reserve/i18n/pt_PT.po
odoo/addons/stock_reserve/i18n/ro.po
odoo/addons/stock_reserve/i18n/ru.po
odoo/addons/stock_reserve/i18n/sk.po
odoo14_addon_stock_reserve-14.0.2.1.2.dist-info/METADATA
odoo14_addon_stock_reserve-14.0.2.1.2.dist-info/WHEEL
odoo14_addon_stock_reserve-14.0.2.1.2.dist-info/top_level.txt
odoo14_addon_stock_reserve-14.0.2.1.2.dist-info/RECORD
